COPYRIGHT.txt
LICENSE.txt
README.rst
setup.py
docs/HISTORY.txt
src/five/__init__.py
src/five.taskqueue.egg-info/PKG-INFO
src/five.taskqueue.egg-info/SOURCES.txt
src/five.taskqueue.egg-info/dependency_links.txt
src/five.taskqueue.egg-info/entry_points.txt
src/five.taskqueue.egg-info/namespace_packages.txt
src/five.taskqueue.egg-info/not-zip-safe
src/five.taskqueue.egg-info/requires.txt
src/five.taskqueue.egg-info/top_level.txt
src/five/taskqueue/__init__.py
src/five/taskqueue/configure.zcml
src/five/taskqueue/processor.py
src/five/taskqueue/service.py
src/five/taskqueue/startup.py
src/five/taskqueue/zope_system.py
src/five/taskqueue/tests/__init__.py
src/five/taskqueue/tests/processor.txt
src/five/taskqueue/tests/test_doctests.py