Metadata-Version: 1.1
Name: five.taskqueue
Version: 0.4.0
Summary: Zope2 integration of z3c.taskqueue
Home-page: http://pypi.python.org/pypi/five.taskqueue
Author: Godefroid Chapelle
Author-email: gotcha@bubblenet.be
License: ZPL 2.1
Keywords: tasks queue jobs cron zope
Platform: UNKNOWN
Classifier: Programming Language :: Python
Classifier: Programming Language :: Python :: 2
Classifier: Programming Language :: Python :: 2.7
Classifier: Framework :: Zope :: 2
Classifier: Framework :: Zope2
